uninstall_dot.py
uninstall_dot-1.0.0.dist-info/licenses/LICENSE
uninstall_dot-1.0.0.dist-info/METADATA
uninstall_dot-1.0.0.dist-info/WHEEL
uninstall_dot-1.0.0.dist-info/entry_points.txt
uninstall_dot-1.0.0.dist-info/top_level.txt
uninstall_dot-1.0.0.dist-info/RECORD
