Metadata-Version: 2.4
Name: uninstall-dot
Version: 1.0.0
Summary: Uninstall .
Author-email: Taben Malik <tabenjmalik@gmail.com>
License-Expression: MIT
Project-URL: Homepage, https://github.com/tabenmalik/uninstall-dot
Project-URL: Issues, https://github.com/tabenmalik/uninstall-dot/issues
Classifier: Environment :: Console
Classifier: Operating System :: OS Independent
Classifier: Programming Language :: Python :: 3
Classifier: Programming Language :: Python :: 3 :: Only
Classifier: Programming Language :: Python :: Implementation :: CPython
Requires-Python: >=3.10
License-File: LICENSE
Requires-Dist: tomli; python_version < "3.11"
Dynamic: license-file
